msb_rpa/__init__.py
msb_rpa/dato_og_tid.py
msb_rpa/generelt.py
msb_rpa/logins.py
msb_rpa/requests.py
msb_rpa/web.py
msb_rpa/windows.py
msb_rpa-0.1.47.dist-info/licenses/LICENSE
tests/__init__.py
msb_rpa-0.1.47.dist-info/METADATA
msb_rpa-0.1.47.dist-info/WHEEL
msb_rpa-0.1.47.dist-info/top_level.txt
msb_rpa-0.1.47.dist-info/RECORD
