Metadata-Version: 2.4
Name: msb_rpa
Version: 0.1.47
Summary: Login metoder og diverse hjælper funktioner til RPA projekter
Author-email: Michael Fredslund Larsen <lfrmi@aarhus.dk>
Classifier: Programming Language :: Python :: 3
Classifier: Operating System :: OS Independent
Requires-Python: >=3.7
License-File: LICENSE
Requires-Dist: pyodbc==5.2.*
Requires-Dist: selenium==4.14.0
Requires-Dist: psutil==5.9.6
Requires-Dist: pyperclip==1.8.2
Requires-Dist: pyautogui==0.9.54
Requires-Dist: pygetwindow==0.0.9
Requires-Dist: pywinauto==0.6.8
Requires-Dist: selenium-wire==5.1.0
Requires-Dist: setuptools==78.1.0
Requires-Dist: blinker==1.7.0
Requires-Dist: requests==2.31.0
Dynamic: license-file
